reporter/__init__.py
reporter/core.py
tests/__init__.py
tests/test_core.py
python_gitlab_reporter-0.0.1.dist-info/METADATA
python_gitlab_reporter-0.0.1.dist-info/WHEEL
python_gitlab_reporter-0.0.1.dist-info/top_level.txt
python_gitlab_reporter-0.0.1.dist-info/RECORD
