Metadata-Version: 2.1
Name: python-gitlab-reporter
Version: 0.0.1
Summary: Handle uncaught exceptions and log them to GitLab as issues.
Home-page: https://github.com/M0r13n/python-gitlab-reporter
Author: Leon Morten Richter
Author-email: leon.morten@gmail.com
License: MIT
Keywords: GitLab,Exceptions,Logging
Platform: UNKNOWN
Classifier: Programming Language :: Python :: 3
Classifier: License :: OSI Approved :: MIT License
Classifier: Operating System :: OS Independent
Classifier: Intended Audience :: Developers
Classifier: Topic :: Communications
Classifier: Typing :: Typed
Requires-Python: >=3.7
Requires-Dist: python-gitlab
